donald/__init__.py
donald/__main__.py
donald/_compat.py
donald/backend.py
donald/manager.py
donald/scheduler.py
donald/tasks.py
donald/types.py
donald/utils.py
donald/worker.py
donald-2.0.1.dist-info/METADATA
donald-2.0.1.dist-info/WHEEL
donald-2.0.1.dist-info/entry_points.txt
donald-2.0.1.dist-info/top_level.txt
donald-2.0.1.dist-info/RECORD
