Metadata-Version: 2.4
Name: donald
Version: 2.0.1
Summary: Task manager for asyncio
Author-email: Kirill Klenov <horneds@gmail.com>
License: MIT License
Project-URL: homepage, https://github.com/klen/donald
Project-URL: repository, https://github.com/klen/donald
Keywords: asyncio,tasks,queue
Classifier: Development Status :: 4 - Beta
Classifier: Intended Audience :: Developers
Classifier: License :: OSI Approved :: MIT License
Classifier: Programming Language :: Python
Classifier: Programming Language :: Python :: 3
Classifier: Programming Language :: Python :: 3.10
Classifier: Programming Language :: Python :: 3.11
Classifier: Programming Language :: Python :: 3.12
Classifier: Programming Language :: Python :: 3.13
Classifier: Framework :: AsyncIO
Requires-Python: >=3.9
Requires-Dist: aio-pika>=9.5.5
Requires-Dist: click>=6.7
Requires-Dist: crontab>=0.22.0
Requires-Dist: async-timeout; python_version < "3.11"
Requires-Dist: typing_extensions; python_version < "3.11"
Provides-Extra: tests
Requires-Dist: redis; extra == "tests"
Requires-Dist: types-redis; extra == "tests"
Requires-Dist: pytest; extra == "tests"
Requires-Dist: pytest-aio; extra == "tests"
Requires-Dist: pytest-mypy; extra == "tests"
Requires-Dist: pytest-redislite; extra == "tests"
Requires-Dist: ruff; extra == "tests"
Provides-Extra: dev
Requires-Dist: pre-commit; extra == "dev"
Requires-Dist: bump2version; extra == "dev"
Provides-Extra: redis
Requires-Dist: redis; extra == "redis"
